{
  "Components": [
    {
      "ComponentName": "LogDirectory",
      "ComponentType": "DirectoryCreate",
      "Comment": "Required by OpenCloudConfig for DSC logging",
      "Path": "C:\\log"
    },
    {
      "ComponentName": "NxLog",
      "ComponentType": "MsiInstall",
      "Comment": "Maintenance Toolchain - not essential for building firefox",
      "Url": "http://nxlog.org/system/files/products/files/1/nxlog-ce-2.9.1504.msi",
      "Name": "NxLog-CE",
      "ProductId": "5E1D25F5-647E-44CA-9223-387230EC02C6"
    },
    {
      "ComponentName": "PaperTrailEncryptionCertificate",
      "ComponentType": "FileDownload",
      "Comment": "Maintenance Toolchain - not essential for building firefox",
      "Source": "https://papertrailapp.com/tools/papertrail-bundle.pem",
      "Target": "C:\\Program Files\\nxlog\\cert\\papertrail-bundle.pem",
      "DependsOn": [
        {
          "ComponentType": "MsiInstall",
          "ComponentName": "NxLog"
        }
      ]
    },
    {
      "ComponentName": "NxLogPaperTrailConfiguration",
      "ComponentType": "ChecksumFileDownload",
      "Comment": "Maintenance Toolchain - not essential for building firefox",
      "Source": "https://raw.githubusercontent.com/MozRelOps/OpenCloudConfig/master/userdata/Configuration/nxlog32.conf",
      "Target": "C:\\Program Files\\nxlog\\conf\\nxlog.conf",
      "DependsOn": [
        {
          "ComponentType": "FileDownload",
          "ComponentName": "PaperTrailEncryptionCertificate"
        }
      ]
    },
    {
      "ComponentName": "Start_nxlog",
      "ComponentType": "ServiceControl",
      "Comment": "Maintenance Toolchain - not essential for building firefox",
      "Name": "nxlog",
      "StartupType": "Automatic",
      "State": "Running",
      "DependsOn": [
        {
          "ComponentType": "ChecksumFileDownload",
          "ComponentName": "NxLogPaperTrailConfiguration"
        }
      ]
    },
    {
      "ComponentName": "GpgForWin",
      "ComponentType": "ExeInstall",
      "Comment": "Maintenance Toolchain - not essential for building firefox",
      "Url": "http://files.gpg4win.org/gpg4win-2.3.0.exe",
      "Arguments": [
        "/S"
      ],
      "Validate": {
        "PathsExist": [
          "C:\\Program Files\\GNU\\GnuPG\\pub\\gpg.exe",
          "C:\\Program Files\\GNU\\GnuPG\\pub\\gpg2.exe"
        ]
      }
    },
    {
      "ComponentName": "SevenZip",
      "ComponentType": "ExeInstall",
      "Comment": "Maintenance Toolchain - not essential for building firefox",
      "Url": "http://7-zip.org/a/7z1602.exe",
      "Arguments": [
        "/S"
      ],
      "Validate": {
        "PathsExist": [
          "C:\\Program Files\\7-Zip\\7z.exe",
          "C:\\Program Files\\7-Zip\\7z.dll"
        ]
      }
    },
    {
      "ComponentName": "SublimeText3",
      "ComponentType": "ExeInstall",
      "Comment": "Maintenance Toolchain - not essential for building firefox",
      "Url": "https://download.sublimetext.com/Sublime%20Text%20Build%203114%20Setup.exe",
      "Arguments": [
        "/VERYSILENT",
        "/NORESTART",
        "/TASKS=\"contextentry\""
      ],
      "Validate": {
        "PathsExist": [
          "C:\\Program Files\\Sublime Text 3\\subl.exe",
          "C:\\Program Files\\Sublime Text 3\\sublime_text.exe"
        ]
      }
    },
    {
      "ComponentName": "SublimeText3_PackagesFolder",
      "ComponentType": "DirectoryCreate",
      "Comment": "Maintenance Toolchain - not essential for building firefox",
      "Path": "C:\\Users\\Administrator\\AppData\\Roaming\\Sublime Text 3\\Packages"
    },
    {
      "ComponentName": "SublimeText3_PackageControl",
      "ComponentType": "FileDownload",
      "Comment": "Maintenance Toolchain - not essential for building firefox",
      "Source": "http://sublime.wbond.net/Package%20Control.sublime-package",
      "Target": "C:\\Users\\Administrator\\AppData\\Roaming\\Sublime Text 3\\Packages\\Package Control.sublime-package",
      "DependsOn": [
        {
          "ComponentType": "ExeInstall",
          "ComponentName": "SublimeText3"
        },
        {
          "ComponentType": "DirectoryCreate",
          "ComponentName": "SublimeText3_PackagesFolder"
        }
      ]
    },
    {
      "ComponentName": "SystemPowerShellProfile",
      "ComponentType": "FileDownload",
      "Comment": "Maintenance Toolchain - not essential for building firefox",
      "Source": "https://raw.githubusercontent.com/MozRelOps/OpenCloudConfig/master/userdata/Configuration/Microsoft.PowerShell_profile.ps1",
      "Target": "C:\\Windows\\System32\\WindowsPowerShell\\v1.0\\Microsoft.PowerShell_profile.ps1"
    },
    {
      "ComponentName": "FsutilDisable8Dot3",
      "ComponentType": "CommandRun",
      "Comment": "Maintenance Toolchain - not essential for building firefox",
      "Command": "fsutil.exe",
      "Arguments": [
        "behavior",
        "set",
        "disable8dot3",
        "1"
      ],
      "Validate": {
        "CommandsReturn": [
          {
            "Command": "fsutil.exe",
            "Arguments": [
              "behavior",
              "query",
              "disable8dot3"
            ],
            "Match": "The registry state is: 1 (Disable 8dot3 name creation on all volumes)."
          }
        ]
      }
    },
    {
      "ComponentName": "FsutilDisableLastAccess",
      "ComponentType": "CommandRun",
      "Comment": "Maintenance Toolchain - not essential for building firefox",
      "Command": "fsutil.exe",
      "Arguments": [
        "behavior",
        "set",
        "disablelastaccess",
        "1"
      ],
      "Validate": {
        "CommandsReturn": [
          {
            "Command": "fsutil.exe",
            "Arguments": [
              "behavior",
              "query",
              "disablelastaccess"
            ],
            "Match": "DisableLastAccess = 1"
          }
        ]
      }
    },
    {
      "ComponentName": "home",
      "ComponentType": "SymbolicLink",
      "Comment": "Maintenance Toolchain - not essential for building firefox",
      "Target": "C:\\Users",
      "Link": "C:\\home"
    },
    {
      "ComponentName": "msys_home",
      "ComponentType": "SymbolicLink",
      "Comment": "Maintenance Toolchain - not essential for building firefox",
      "Target": "C:\\Users",
      "Link": "C:\\mozilla-build\\msys\\home",
      "DependsOn": [
        {
          "ComponentType": "ExeInstall",
          "ComponentName": "MozillaBuildSetup"
        }
      ]
    },
    {
      "ComponentName": "MozillaBuildSetup",
      "ComponentType": "ExeInstall",
      "Comment": "Base Firefox on Windows build requirement",
      "Arguments": [
        "/S",
        "/D=C:\\mozilla-build"
      ],
      "Url": "http://ftp.mozilla.org/pub/mozilla/libraries/win32/MozillaBuildSetup-2.2.0.exe",
      "Validate": {
        "PathsExist": [
          "C:\\mozilla-build\\info-zip\\unzip.exe",
          "C:\\mozilla-build\\info-zip\\zip.exe",
          "C:\\mozilla-build\\msys\\bin\\sh.exe",
          "C:\\mozilla-build\\python\\python.exe"
        ],
        "FilesContain": [
          {
            "Path": "C:\\mozilla-build\\VERSION",
            "Match": "2.2.0"
          }
        ]
      }
    },
    {
      "ComponentName": "MercurialPythonPatch",
      "ComponentType": "SymbolicLink",
      "Comment": "Required by hg extensions",
      "DependsOn": [
        {
          "ComponentType": "ExeInstall",
          "ComponentName": "MozillaBuildSetup"
        }
      ],
      "Target": "C:\\mozilla-build\\python\\python27.dll",
      "Link": "C:\\mozilla-build\\python\\Scripts\\python27.dll"
    },
    {
      "ComponentName": "MercurialUse1Config",
      "ComponentType": "FileDownload",
      "Comment": "Required by CloneBundles (hg extension)",
      "DependsOn": [
        {
          "ComponentType": "ExeInstall",
          "ComponentName": "MozillaBuildSetup"
        }
      ],
      "Source": "https://raw.githubusercontent.com/MozRelOps/OpenCloudConfig/master/userdata/Configuration/Mercurial/mercurial.us-east-1.ini",
      "Target": "C:\\mozilla-build\\python\\Scripts\\mercurial.us-east-1.ini"
    },
    {
      "ComponentName": "MercurialUsw1Config",
      "ComponentType": "FileDownload",
      "Comment": "Required by CloneBundles (hg extension)",
      "DependsOn": [
        {
          "ComponentType": "ExeInstall",
          "ComponentName": "MozillaBuildSetup"
        }
      ],
      "Source": "https://raw.githubusercontent.com/MozRelOps/OpenCloudConfig/master/userdata/Configuration/Mercurial/mercurial.us-west-1.ini",
      "Target": "C:\\mozilla-build\\python\\Scripts\\mercurial.us-west-1.ini"
    },
    {
      "ComponentName": "MercurialUsw2Config",
      "ComponentType": "FileDownload",
      "Comment": "Required by CloneBundles (hg extension)",
      "DependsOn": [
        {
          "ComponentType": "ExeInstall",
          "ComponentName": "MozillaBuildSetup"
        }
      ],
      "Source": "https://raw.githubusercontent.com/MozRelOps/OpenCloudConfig/master/userdata/Configuration/Mercurial/mercurial.us-west-2.ini",
      "Target": "C:\\mozilla-build\\python\\Scripts\\mercurial.us-west-2.ini"
    },
    {
      "ComponentName": "env_MOZILLABUILD",
      "ComponentType": "EnvironmentVariableSet",
      "Comment": "Absolutely required for mozharness builds. Python will fall in a heap, throwing misleading exceptions without this. :)",
      "DependsOn": [
        {
          "ComponentType": "ExeInstall",
          "ComponentName": "MozillaBuildSetup"
        }
      ],
      "Name": "MOZILLABUILD",
      "Value": "C:\\mozilla-build",
      "Target": "Machine"
    },
    {
      "ComponentName": "env_PATH",
      "ComponentType": "EnvironmentVariableUniquePrepend",
      "DependsOn": [
        {
          "ComponentType": "ExeInstall",
          "ComponentName": "MozillaBuildSetup"
        }
      ],
      "Name": "PATH",
      "Values": [
        "C:\\mozilla-build\\7zip",
        "C:\\mozilla-build\\info-zip",
        "C:\\mozilla-build\\kdiff3",
        "C:\\mozilla-build\\moztools-x64\\bin",
        "C:\\mozilla-build\\mozmake",
        "C:\\mozilla-build\\msys\\bin",
        "C:\\mozilla-build\\msys\\local\\bin",
        "C:\\mozilla-build\\nsis-3.0b3",
        "C:\\mozilla-build\\nsis-2.46u",
        "C:\\mozilla-build\\python",
        "C:\\mozilla-build\\python\\Scripts",
        "C:\\mozilla-build\\upx391w",
        "C:\\mozilla-build\\wget"
      ],
      "Target": "Machine"
    },
    {
      "ComponentName": "reg_WindowsErrorReportingLocalDumps",
      "ComponentType": "RegistryKeySet",
      "Comment": "",
      "Key": "HKEY_LOCAL_MACHINE\\SOFTWARE\\Microsoft\\Windows\\Windows Error Reporting",
      "ValueName": "LocalDumps"
    },
    {
      "ComponentName": "reg_WindowsErrorReportingDontShowUI",
      "ComponentType": "RegistryValueSet",
      "Comment": "",
      "Key": "HKEY_LOCAL_MACHINE\\SOFTWARE\\Microsoft\\Windows\\Windows Error Reporting",
      "ValueName": "DontShowUI",
      "ValueType": "Dword",
      "ValueData": "0x00000001",
      "Hex": true
    },
    {
      "ComponentName": "GenericWorkerDirectory",
      "ComponentType": "DirectoryCreate",
      "Path": "C:\\generic-worker"
    },
    {
      "ComponentName": "GenericWorkerDownload",
      "ComponentType": "ChecksumFileDownload",
      "DependsOn": [
        {
          "ComponentType": "DirectoryCreate",
          "ComponentName": "GenericWorkerDirectory"
        }
      ],
      "Source": "https://github.com/taskcluster/generic-worker/releases/download/v3.0.0alpha1/generic-worker-windows-386.exe",
      "Target": "C:\\generic-worker\\generic-worker.exe"
    },
    {
      "ComponentName": "LiveLogDownload",
      "ComponentType": "ChecksumFileDownload",
      "DependsOn": [
        {
          "ComponentType": "DirectoryCreate",
          "ComponentName": "GenericWorkerDirectory"
        }
      ],
      "Source": "https://github.com/taskcluster/livelog/releases/download/v1.0.0/livelog-windows-386.exe",
      "Target": "C:\\generic-worker\\livelog.exe"
    },
    {
      "ComponentName": "LiveLog_Get",
      "ComponentType": "FirewallRule",
      "Protocol": "TCP",
      "LocalPort": 60022,
      "Direction": "Inbound",
      "Action": "Allow"
    },
    {
      "ComponentName": "LiveLog_Put",
      "ComponentType": "FirewallRule",
      "Protocol": "TCP",
      "LocalPort": 60023,
      "Direction": "Inbound",
      "Action": "Allow"
    },
    {
      "ComponentName": "GenericWorkerInstall",
      "ComponentType": "CommandRun",
      "Command": "C:\\generic-worker\\generic-worker.exe",
      "Arguments": [
        "install",
        "startup",
        "--config",
        "C:\\generic-worker\\generic-worker.config"
      ],
      "DependsOn": [
        {
          "ComponentType": "ChecksumFileDownload",
          "ComponentName": "GenericWorkerDownload"
        },
        {
          "ComponentType": "ChecksumFileDownload",
          "ComponentName": "LiveLogDownload"
        },
        {
          "ComponentType": "FirewallRule",
          "ComponentName": "LiveLog_Get"
        },
        {
          "ComponentType": "FirewallRule",
          "ComponentName": "LiveLog_Put"
        }
      ],
      "Validate": {
        "PathsExist": [
          "C:\\generic-worker\\run-generic-worker.bat",
          "C:\\generic-worker\\generic-worker.exe"
        ],
        "CommandsReturn": [
          {
            "Command": "C:\\generic-worker\\generic-worker.exe",
            "Arguments": [
              "--version"
            ],
            "Match": "generic-worker 3.0.0alpha1"
          }
        ]
      }
    },
    {
      "ComponentName": "HgShared",
      "ComponentType": "DirectoryCreate",
      "Comment": "required by hg caches",
      "Path": "C:\\builds\\hg-shared"
    },
    {
      "ComponentName": "HgSharedAccessRights",
      "ComponentType": "CommandRun",
      "Comment": "allows builds to use `hg share ...`",
      "Command": "icacls.exe",
      "Arguments": [
        "C:\\builds\\hg-shared",
        "/grant",
        "Everyone:(OI)(CI)F"
      ],
      "DependsOn": [
        {
          "ComponentType": "DirectoryCreate",
          "ComponentName": "HgShared"
        }
      ]
    },
    {
      "ComponentName": "MozillaCentralCacheCreate",
      "ComponentType": "CommandRun",
      "Comment": "required by firefox builds",
      "Command": "C:\\mozilla-build\\python\\Scripts\\hg.exe",
      "Arguments": [
        "clone",
        "-U",
        "https://hg.mozilla.org/mozilla-central",
        "C:\\builds\\hg-shared\\mozilla-central"
      ],
      "DependsOn": [
        {
          "ComponentType": "ExeInstall",
          "ComponentName": "MozillaBuildSetup"
        },
        {
          "ComponentType": "SymbolicLink",
          "ComponentName": "MercurialPythonPatch"
        },
        {
          "ComponentType": "DirectoryCreate",
          "ComponentName": "HgShared"
        }
      ],
      "Validate": {
        "PathsExist": [
          "C:\\builds\\hg-shared\\mozilla-central\\.hg"
        ]
      }
    },
    {
      "ComponentName": "MozillaCentralCacheUpdate",
      "ComponentType": "CommandRun",
      "Comment": "keeps the cache up to date on subsequent runs/reboots",
      "Command": "C:\\mozilla-build\\python\\Scripts\\hg.exe",
      "Arguments": [
        "pull",
        "-R",
        "C:\\builds\\hg-shared\\mozilla-central"
      ],
      "DependsOn": [
        {
          "ComponentType": "CommandRun",
          "ComponentName": "MozillaCentralCacheCreate"
        }
      ]
    }
  ]
}
